iridauploader/__init__.py
iridauploader/api/__init__.py
iridauploader/api/api_calls.py
iridauploader/api/exceptions/__init__.py
iridauploader/api/exceptions/file_error.py
iridauploader/api/exceptions/irida_connection_error.py
iridauploader/api/exceptions/irida_resource_error.py
iridauploader/api/exceptions/irida_upload_canceled_exception.py
iridauploader/config/__init__.py
iridauploader/config/config.py
iridauploader/core/__init__.py
iridauploader/core/api_handler.py
iridauploader/core/cli.py
iridauploader/core/exit_return.py
iridauploader/core/file_size_validator.py
iridauploader/core/logger.py
iridauploader/core/model_validator.py
iridauploader/core/parsing_handler.py
iridauploader/core/uniform_file_count_validator.py
iridauploader/core/upload.py
iridauploader/core/upload_helpers.py
iridauploader/gui/__init__.py
iridauploader/gui/colours.py
iridauploader/gui/config.py
iridauploader/gui/gui.py
iridauploader/gui/main_dialog.py
iridauploader/gui/threads.py
iridauploader/gui/tools.py
iridauploader/gui/widgets.py
iridauploader/messaging/__init__.py
iridauploader/messaging/pubsub.py
iridauploader/model/__init__.py
iridauploader/model/directory_status.py
iridauploader/model/metadata.py
iridauploader/model/project.py
iridauploader/model/sample.py
iridauploader/model/sequence_file.py
iridauploader/model/sequencing_run.py
iridauploader/model/validation_result.py
iridauploader/model/exceptions/__init__.py
iridauploader/model/exceptions/model_validation_error.py
iridauploader/parsers/__init__.py
iridauploader/parsers/base_parser.py
iridauploader/parsers/common.py
iridauploader/parsers/parsers.py
iridauploader/parsers/directory/__init__.py
iridauploader/parsers/directory/parser.py
iridauploader/parsers/directory/sample_parser.py
iridauploader/parsers/directory/validation.py
iridauploader/parsers/exceptions/__init__.py
iridauploader/parsers/exceptions/directory_error.py
iridauploader/parsers/exceptions/file_size_error.py
iridauploader/parsers/exceptions/sample_sheet_error.py
iridauploader-0.9.5.dist-info/LICENSE
iridauploader-0.9.5.dist-info/METADATA
iridauploader-0.9.5.dist-info/WHEEL
iridauploader-0.9.5.dist-info/entry_points.txt
iridauploader-0.9.5.dist-info/top_level.txt
iridauploader-0.9.5.dist-info/RECORD
