Metadata-Version: 2.1
Name: iridauploader
Version: 0.9.5
Summary: IRIDA uploader: upload NGS data to IRIDA system
Home-page: https://github.com/phac-nml/irida-uploader
Author: Jeffrey Thiessen
Author-email: jeffrey.thiessen@canada.ca
License: Apache-2.0
Keywords: IRIDA NGS uploader
Classifier: Programming Language :: Python :: 3
Classifier: License :: OSI Approved :: Apache Software License
Classifier: Operating System :: OS Independent
Requires-Python: >=3.7
License-File: LICENSE
Requires-Dist: urllib3<2.3.0
Requires-Dist: rauth
Requires-Dist: requests
Requires-Dist: chardet
Requires-Dist: appdirs
Requires-Dist: cerberus
Requires-Dist: argparse
Requires-Dist: requests-toolbelt
Provides-Extra: gui
Requires-Dist: PyQt5==5.15.2; extra == "gui"
Requires-Dist: PyQt5-stubs==5.14.2.2; extra == "gui"
Provides-Extra: test
Requires-Dist: pytest; extra == "test"
Requires-Dist: coverage; extra == "test"
Provides-Extra: windows
Requires-Dist: pynsist; extra == "windows"
